Metadata-Version: 1.0
Name: strcolor
Version: 1.9
Summary: 一个用来进行颜色打印的便捷工具
Home-page: https://github.com/dugudongfangshuo
Author: dugudongfangshuo
Author-email: 2310775260@qq.com
License: MIT
Platform: UNKNOWN
